books_dl/client.py
books_dl/__main__.py
books_dl/__init__.py
books_dl/utils/_decode.cpython-37m-x86_64-linux-gnu.so
books_dl/utils/decode.py
books_dl/utils/__init__.py
books_dl/epub/container.py
books_dl/epub/__init__.py
books_dl/epub/package.py
books_com_tw_dl-1.1.2.0.dist-info/LICENSE
books_com_tw_dl-1.1.2.0.dist-info/RECORD
books_com_tw_dl-1.1.2.0.dist-info/METADATA
books_com_tw_dl-1.1.2.0.dist-info/WHEEL
books_com_tw_dl-1.1.2.0.dist-info/top_level.txt
books_com_tw_dl-1.1.2.0.dist-info/entry_points.txt
