Metadata-Version: 2.1
Name: books-com-tw-dl
Version: 1.1.2.0
Summary: books.com.tw book downloader
Home-page: https://github.com/lifegpc/books-dl
Author: lifegpc
Author-email: root@lifegpc.com
License: GNU General Public License v3 or later
Keywords: downloader
Classifier: License :: OSI Approved :: GNU General Public License v3 or later (GPLv3+)
Classifier: Programming Language :: Python :: 3.7
Requires-Python: >=3.6
License-File: LICENSE
Requires-Dist: requests
